microcosm_sqlite/__init__.py
microcosm_sqlite/alembic.py
microcosm_sqlite/constants.py
microcosm_sqlite/context.py
microcosm_sqlite/dataset.py
microcosm_sqlite/errors.py
microcosm_sqlite/factories.py
microcosm_sqlite/identifiers.py
microcosm_sqlite/models.py
microcosm_sqlite/stores.py
microcosm_sqlite/types.py
microcosm_sqlite/builders/__init__.py
microcosm_sqlite/builders/csv.py
microcosm_sqlite/cmd/__init__.py
microcosm_sqlite/cmd/check_migration.py
microcosm_sqlite/cmd/migrate.py
microcosm_sqlite/dumpers/__init__.py
microcosm_sqlite/dumpers/csv.py
microcosm_sqlite-2.0.0.dist-info/LICENSE
microcosm_sqlite-2.0.0.dist-info/METADATA
microcosm_sqlite-2.0.0.dist-info/WHEEL
microcosm_sqlite-2.0.0.dist-info/entry_points.txt
microcosm_sqlite-2.0.0.dist-info/top_level.txt
microcosm_sqlite-2.0.0.dist-info/RECORD
