Metadata-Version: 2.1
Name: microcosm-sqlite
Version: 2.0.0
Summary: Opinionated persistence with SQLite
Home-page: https://github.com/globality-corp/microcosm-sqlite
Author: Globality Engineering
Author-email: engineering@globality.com
Keywords: microcosm
Requires-Python: >=3.11
License-File: LICENSE
Requires-Dist: SQLAlchemy-Utils >=0.33.3
Requires-Dist: SQLAlchemy >=1.2.0
Requires-Dist: alembic >=1.0.11
Requires-Dist: microcosm >=4.0.0
Provides-Extra: lint
Requires-Dist: flake8 ; extra == 'lint'
Requires-Dist: flake8-print ; extra == 'lint'
Requires-Dist: flake8-isort ; extra == 'lint'
Provides-Extra: test
Requires-Dist: coverage >=3.7.1 ; extra == 'test'
Requires-Dist: PyHamcrest >=1.8.5 ; extra == 'test'
Requires-Dist: pytest-cov >=5.0.0 ; extra == 'test'
Requires-Dist: pytest >=6.2.5 ; extra == 'test'
Provides-Extra: typehinting
Requires-Dist: mypy ; extra == 'typehinting'
Requires-Dist: types-setuptools ; extra == 'typehinting'
